{
    "name": "UFC 326: Holloway vs. Oliveira",
    "date": "2026-03-07",
    "location": "",
    "venue": "T-Mobile Arena",
    "fights": [
        {
            "weightclass": "Peso-leve",
            "red corner": {
                "name": "Max Holloway",
                "ranking": "",
                "odds": "-200",
                "link": "https://www.ufc.com.br/athlete/max-holloway",
                "result": "Loss"
            },
            "blue corner": {
                "name": "Charles Oliveira",
                "ranking": "3",
                "odds": "+165",
                "link": "https://www.ufc.com.br/athlete/charles-oliveira",
                "result": "Win"
            },
            "round": "5",
            "time": "5:00",
            "method": "Decision - Unanimous"
        },
        {
            "weightclass": "Peso-médio",
            "red corner": {
                "name": "Caio Borralho",
                "ranking": "7",
                "odds": "-245",
                "link": "https://www.ufc.com.br/athlete/caio-borralho",
                "result": "Win"
            },
            "blue corner": {
                "name": "Reinier de Ridder",
                "ranking": "8",
                "odds": "+200",
                "link": "https://www.ufc.com.br/athlete/reinier-de-ridder",
                "result": "Loss"
            },
            "round": "3",
            "time": "5:00",
            "method": "Decision - Unanimous"
        },
        {
            "weightclass": "Peso-galo",
            "red corner": {
                "name": "Rob Font",
                "ranking": "13",
                "odds": "+235",
                "link": "https://www.ufc.com.br/athlete/rob-font",
                "result": "Loss"
            },
            "blue corner": {
                "name": "Raul Rosas Jr.",
                "ranking": "Unranked",
                "odds": "-290",
                "link": "https://www.ufc.com.br/athlete/raul-rosas-jr",
                "result": "Win"
            },
            "round": "3",
            "time": "5:00",
            "method": "Decision - Unanimous"
        },
        {
            "weightclass": "Peso-leve",
            "red corner": {
                "name": "Drew Dober",
                "ranking": "Unranked",
                "odds": "-180",
                "link": "https://www.ufc.com.br/athlete/drew-dober",
                "result": "Win"
            },
            "blue corner": {
                "name": "Michael Johnson",
                "ranking": "Unranked",
                "odds": "+150",
                "link": "https://www.ufc.com.br/athlete/michael-johnson",
                "result": "Loss"
            },
            "round": "2",
            "time": "1:53",
            "method": "KO/TKO"
        },
        {
            "weightclass": "Peso-médio",
            "red corner": {
                "name": "Gregory Rodrigues",
                "ranking": "13",
                "odds": "-160",
                "link": "https://www.ufc.com.br/athlete/gregory-rodrigues",
                "result": "Win"
            },
            "blue corner": {
                "name": "Brunno Ferreira",
                "ranking": "15",
                "odds": "+135",
                "link": "https://www.ufc.com.br/athlete/brunno-ferreira",
                "result": "Loss"
            },
            "round": "1",
            "time": "1:47",
            "method": "KO/TKO"
        },
        {
            "weightclass": "Peso-galo",
            "red corner": {
                "name": "Cody Garbrandt",
                "ranking": "Unranked",
                "odds": "+135",
                "link": "https://www.ufc.com.br/athlete/cody-garbrandt",
                "result": "Win"
            },
            "blue corner": {
                "name": "Xiao Long",
                "ranking": "Unranked",
                "odds": "-160",
                "link": "https://www.ufc.com.br/athlete/shiyao-ron",
                "result": "Loss"
            },
            "round": "3",
            "time": "5:00",
            "method": "Decision - Unanimous"
        },
        {
            "weightclass": "Peso-médio",
            "red corner": {
                "name": "Donte Johnson",
                "ranking": "Unranked",
                "odds": "-800",
                "link": "https://www.ufc.com.br/athlete/donte-johnson",
                "result": "Win"
            },
            "blue corner": {
                "name": "Cody Brundage",
                "ranking": "Unranked",
                "odds": "+550",
                "link": "https://www.ufc.com.br/athlete/cody-brundage",
                "result": "Loss"
            },
            "round": "3",
            "time": "5:00",
            "method": "Decision - Split"
        },
        {
            "weightclass": "Peso-pena",
            "red corner": {
                "name": "Ricky Turcios",
                "ranking": "Unranked",
                "odds": "+155",
                "link": "https://www.ufc.com.br/athlete/ricky-turcios",
                "result": "Loss"
            },
            "blue corner": {
                "name": "Alberto Montes",
                "ranking": "Unranked",
                "odds": "-185",
                "link": "https://www.ufc.com.br/athlete/alberto-montes",
                "result": "Win"
            },
            "round": "2",
            "time": "0:40",
            "method": "Submission"
        },
        {
            "weightclass": "Peso-mosca",
            "red corner": {
                "name": "Cody Durden",
                "ranking": "Unranked",
                "odds": "+140",
                "link": "https://www.ufc.com.br/athlete/cody-durden",
                "result": "Loss"
            },
            "blue corner": {
                "name": "Nyamjargal Tumendemberel",
                "ranking": "Unranked",
                "odds": "-165",
                "link": "https://www.ufc.com.br/athlete/nyamjargal-tumendemberel",
                "result": "Win"
            },
            "round": "3",
            "time": "5:00",
            "method": "Decision - Unanimous"
        },
        {
            "weightclass": "Peso-mosca",
            "red corner": {
                "name": "Sumudaerji",
                "ranking": "Unranked",
                "odds": "-220",
                "link": "https://www.ufc.com.br/athlete/su-mudaerji",
                "result": "Win"
            },
            "blue corner": {
                "name": "Jesus Aguilar",
                "ranking": "Unranked",
                "odds": "+180",
                "link": "https://www.ufc.com.br/athlete/jesus-aguilar",
                "result": "Loss"
            },
            "round": "3",
            "time": "5:00",
            "method": "Decision - Unanimous"
        },
        {
            "weightclass": "Peso meio-pesado",
            "red corner": {
                "name": "Rafael Tobias",
                "ranking": "Unranked",
                "odds": "-185",
                "link": "https://www.ufc.com.br/athlete/rafael-tobias",
                "result": "Loss"
            },
            "blue corner": {
                "name": "Diyar Nurgozhay",
                "ranking": "Unranked",
                "odds": "+155",
                "link": "https://www.ufc.com.br/athlete/diyar-nurgozhay",
                "result": "Win"
            },
            "round": "3",
            "time": "5:00",
            "method": "Decision - Unanimous"
        },
        {
            "weightclass": "Peso meio-pesado",
            "red corner": {
                "name": "Luke Fernandez",
                "ranking": "Unranked",
                "odds": "-225",
                "link": "https://www.ufc.com.br/athlete/luke-fernandez",
                "result": "Loss"
            },
            "blue corner": {
                "name": "Rodolfo Bellato",
                "ranking": "Unranked",
                "odds": "+185",
                "link": "https://www.ufc.com.br/athlete/rodolfo-bellato",
                "result": "Win"
            },
            "round": "1",
            "time": "2:42",
            "method": "KO/TKO"
        }
    ]
}